cloudmesh_covid-4.4.11-nspkg.pth
cloudmesh/covid/__init__.py
cloudmesh/covid/__version__.py
cloudmesh/covid/api/__init__.py
cloudmesh/covid/api/manager.py
cloudmesh/covid/command/__init__.py
cloudmesh/covid/command/covid.py
cloudmesh/covid/data/__init__.py
cloudmesh/covid/data/world.py
cloudmesh_covid-4.4.11.dist-info/LICENSE
cloudmesh_covid-4.4.11.dist-info/METADATA
cloudmesh_covid-4.4.11.dist-info/WHEEL
cloudmesh_covid-4.4.11.dist-info/namespace_packages.txt
cloudmesh_covid-4.4.11.dist-info/top_level.txt
cloudmesh_covid-4.4.11.dist-info/RECORD
